{"Biomes": {"Glacial Strata": [{"PrimaryObjective": "Egg Hunt", "SecondaryObjective": "Gunk Seeds", "Complexity": "2", "Length": "2", "CodeName": "Sudden Hell", "id": 11915, "season": "s0"}, {"PrimaryObjective": "Point Extraction", "SecondaryObjective": "Fester Fleas", "Complexity": "3", "Length": "2", "CodeName": "Whalepiper's Fangs", "id": 11916, "season": "s0"}, {"PrimaryObjective": "Industrial Sabotage", "SecondaryObjective": "Hollomite", "Complexity": "1", "Length": "2", "CodeName": "Dusty Break", "id": 11917, "season": "s0"}, {"PrimaryObjective": "Elimination", "SecondaryObjective": "Gunk Seeds", "MissionWarnings": ["Swarmageddon"], "Complexity": "3", "Length": "3", "CodeName": "Freak Hulrum", "id": 11918, "season": "s0"}], "Crystalline Caverns": [{"PrimaryObjective": "Mining Expedition", "SecondaryObjective": "Fester Fleas", "Complexity": "1", "Length": "1", "CodeName": "Infested Crypt", "id": 11905, "season": "s0"}, {"PrimaryObjective": "Egg Hunt", "SecondaryObjective": "Fester Fleas", "Complexity": "1", "Length": "1", "CodeName": "Impure Sadness", "id": 11906, "season": "s0"}, {"PrimaryObjective": "On-Site Refining", "SecondaryObjective": "Ebonuts", "Complexity": "2", "Length": "2", "CodeName": "Foul Blackout", "id": 11907, "season": "s0"}, {"PrimaryObjective": "Industrial Sabotage", "SecondaryObjective": "Fossils", "MissionWarnings": ["Elite Threat"], "MissionMutator": "Volatile Guts", "Complexity": "2", "Length": "2", "CodeName": "Raw Summit", "id": 11908, "season": "s0"}], "Azure Weald": [{"PrimaryObjective": "Elimination", "SecondaryObjective": "Hollomite", "Complexity": "2", "Length": "2", "CodeName": "Weeping Honor", "id": 11919, "season": "s0"}, {"PrimaryObjective": "Escort Duty", "SecondaryObjective": "ApocaBlooms", "Complexity": "2", "Length": "2", "CodeName": "True Patrol", "id": 11920, "season": "s0"}, {"PrimaryObjective": "On-Site Refining", "SecondaryObjective": "Fester Fleas", "Complexity": "3", "Length": "2", "CodeName": "Driller's Fence", "id": 11921, "season": "s0"}, {"PrimaryObjective": "Egg Hunt", "SecondaryObjective": "ApocaBlooms", "MissionWarnings": ["Exploder Infestation"], "Complexity": "2", "Length": "2", "CodeName": "Fast Run", "id": 11922, "season": "s0"}, {"PrimaryObjective": "Mining Expedition", "SecondaryObjective": "Ebonuts", "MissionWarnings": ["Cave Leech Cluster", "Exploder Infestation"], "Complexity": "2", "Length": "2", "CodeName": "Deadly Dome", "id": 11923, "season": "s0"}], "Fungus Bogs": [{"PrimaryObjective": "Salvage Operation", "SecondaryObjective": "Gunk Seeds", "Complexity": "2", "Length": "2", "CodeName": "Deadman's Shroud", "id": 11910, "season": "s0"}, {"PrimaryObjective": "Elimination", "SecondaryObjective": "Fossils", "MissionMutator": "Volatile Guts", "Complexity": "3", "Length": "3", "CodeName": "Rapid Tomb", "id": 11911, "season": "s0"}, {"PrimaryObjective": "Egg Hunt", "SecondaryObjective": "Hollomite", "MissionMutator": "Gold Rush", "Complexity": "2", "Length": "2", "CodeName": "Bared Trail", "id": 11912, "season": "s0"}, {"PrimaryObjective": "Mining Expedition", "SecondaryObjective": "Fossils", "MissionMutator": "Low Gravity", "Complexity": "3", "Length": "3", "CodeName": "Broken Land", "id": 11914, "season": "s0"}, {"PrimaryObjective": "Mining Expedition", "SecondaryObjective": "Fossils", "MissionWarnings": ["Lithophage Outbreak"], "MissionMutator": "Low Gravity", "Complexity": "3", "Length": "3", "CodeName": "Broken Land", "id": 11933, "season": "s4"}, {"PrimaryObjective": "On-Site Refining", "SecondaryObjective": "Ebonuts", "MissionWarnings": ["Lithophage Outbreak"], "MissionMutator": "Low Gravity", "Complexity": "2", "Length": "2", "CodeName": "Crazy Hate", "id": 11934, "season": "s4"}], "Radioactive Exclusion Zone": [{"PrimaryObjective": "Mining Expedition", "SecondaryObjective": "Hollomite", "Complexity": "1", "Length": "2", "CodeName": "Crumbly Pocket", "id": 11909, "season": "s0"}, {"PrimaryObjective": "Egg Hunt", "SecondaryObjective": "Fester Fleas", "MissionMutator": "Critical Weakness", "Complexity": "2", "Length": "3", "CodeName": "Ruptured Cell", "id": 11913, "season": "s0"}, {"PrimaryObjective": "Egg Hunt", "SecondaryObjective": "Fester Fleas", "MissionWarnings": ["Lithophage Outbreak"], "MissionMutator": "Critical Weakness", "Complexity": "2", "Length": "3", "CodeName": "Ruptured Cell", "id": 11932, "season": "s4"}, {"PrimaryObjective": "Elimination", "SecondaryObjective": "Boolo Caps", "MissionWarnings": ["Lithophage Outbreak"], "MissionMutator": "Critical Weakness", "Complexity": "3", "Length": "3", "CodeName": "Shattered Hideout", "id": 11935, "season": "s4"}]}, "timestamp": "2024-04-16T13:00:00Z"}