{"Biomes": {"Glacial Strata": [{"PrimaryObjective": "Mining Expedition", "SecondaryObjective": "Fester Fleas", "MissionMutator": "Mineral Mania", "Complexity": "2", "Length": "2", "CodeName": "Crumbling Thunder", "id": 14023, "season": "s0"}, {"PrimaryObjective": "Escort Duty", "SecondaryObjective": "Fossils", "MissionMutator": "Mineral Mania", "Complexity": "3", "Length": "3", "CodeName": "High Cellar", "id": 14025, "season": "s0"}, {"PrimaryObjective": "Egg Hunt", "SecondaryObjective": "Fester Fleas", "Complexity": "2", "Length": "2", "CodeName": "True Grave", "id": 14026, "season": "s0"}, {"PrimaryObjective": "Egg Hunt", "SecondaryObjective": "Fester Fleas", "MissionWarnings": ["Lithophage Outbreak"], "Complexity": "2", "Length": "2", "CodeName": "True Grave", "id": 14045, "season": "s4"}, {"PrimaryObjective": "Point Extraction", "SecondaryObjective": "Boolo Caps", "MissionWarnings": ["Lithophage Outbreak"], "Complexity": "3", "Length": "2", "CodeName": "Final Inferno", "id": 14047, "season": "s4"}], "Salt Pits": [{"PrimaryObjective": "Mining Expedition", "SecondaryObjective": "Fossils", "Complexity": "1", "Length": "1", "CodeName": "Pale Skull", "id": 14013, "season": "s0"}, {"PrimaryObjective": "Egg Hunt", "SecondaryObjective": "Hollomite", "Complexity": "1", "Length": "1", "CodeName": "Dirty Pocket", "id": 14014, "season": "s0"}, {"PrimaryObjective": "On-Site Refining", "SecondaryObjective": "ApocaBlooms", "Complexity": "2", "Length": "2", "CodeName": "Broken Senit", "id": 14015, "season": "s0"}, {"PrimaryObjective": "Industrial Sabotage", "SecondaryObjective": "ApocaBlooms", "MissionWarnings": ["Elite Threat"], "Complexity": "2", "Length": "2", "CodeName": "Bared Strike", "id": 14016, "season": "s0"}], "Azure Weald": [{"PrimaryObjective": "Elimination", "SecondaryObjective": "Boolo Caps", "Complexity": "2", "Length": "2", "CodeName": "Ruptured Arm", "id": 14027, "season": "s0"}, {"PrimaryObjective": "Escort Duty", "SecondaryObjective": "Ebonuts", "Complexity": "2", "Length": "2", "CodeName": "Colossal Abyss", "id": 14028, "season": "s0"}, {"PrimaryObjective": "On-Site Refining", "SecondaryObjective": "Fester Fleas", "Complexity": "3", "Length": "2", "CodeName": "Dreadful Arm", "id": 14029, "season": "s0"}, {"PrimaryObjective": "Industrial Sabotage", "SecondaryObjective": "Fossils", "Complexity": "1", "Length": "2", "CodeName": "Pure Let-down", "id": 14030, "season": "s0"}, {"PrimaryObjective": "Point Extraction", "SecondaryObjective": "Gunk Seeds", "MissionWarnings": ["Elite Threat", "Lethal Enemies"], "Complexity": "3", "Length": "2", "CodeName": "Blunt End", "id": 14031, "season": "s0"}], "Radioactive Exclusion Zone": [{"PrimaryObjective": "Mining Expedition", "SecondaryObjective": "Boolo Caps", "Complexity": "1", "Length": "2", "CodeName": "Ancient Blackness", "id": 14017, "season": "s0"}, {"PrimaryObjective": "Salvage Operation", "SecondaryObjective": "Fossils", "Complexity": "2", "Length": "2", "CodeName": "Burning Tomb", "id": 14018, "season": "s0"}, {"PrimaryObjective": "Point Extraction", "SecondaryObjective": "Dystrum", "MissionWarnings": ["Regenerative Bugs"], "Complexity": "3", "Length": "3", "CodeName": "Snowy Break", "id": 14019, "season": "s0"}, {"PrimaryObjective": "Elimination", "SecondaryObjective": "Fossils", "MissionWarnings": ["Cave Leech Cluster"], "Complexity": "3", "Length": "3", "CodeName": "Loser's Gods", "id": 14020, "season": "s0"}], "Dense Biozone": [{"PrimaryObjective": "Point Extraction", "SecondaryObjective": "Ebonuts", "Complexity": "3", "Length": "2", "CodeName": "Morning Fence", "id": 14022, "season": "s0"}, {"PrimaryObjective": "Salvage Operation", "SecondaryObjective": "Gunk Seeds", "MissionWarnings": ["Lithophage Outbreak"], "Complexity": "3", "Length": "3", "CodeName": "Scout's Face", "id": 14046, "season": "s4"}], "Hollow Bough": [{"PrimaryObjective": "Egg Hunt", "SecondaryObjective": "Gunk Seeds", "Complexity": "2", "Length": "2", "CodeName": "Engineer's Doom", "id": 14021, "season": "s0"}, {"PrimaryObjective": "Elimination", "SecondaryObjective": "Fossils", "Complexity": "3", "Length": "3", "CodeName": "Giant Breach", "id": 14024, "season": "s0"}, {"PrimaryObjective": "Elimination", "SecondaryObjective": "Fossils", "MissionWarnings": ["Lithophage Outbreak"], "Complexity": "3", "Length": "3", "CodeName": "Giant Breach", "id": 14043, "season": "s4"}, {"PrimaryObjective": "Point Extraction", "SecondaryObjective": "Dystrum", "MissionWarnings": ["Lithophage Outbreak"], "MissionMutator": "Gold Rush", "Complexity": "3", "Length": "3", "CodeName": "Dastardly Jewel", "id": 14048, "season": "s4"}]}, "timestamp": "2024-04-17T15:00:00Z"}