{"s4": {"Biomes": {"Crystalline Caverns": [{"PrimaryObjective": "Egg Hunt", "SecondaryObjective": "ApocaBlooms", "Complexity": "1", "Length": "1", "CodeName": "Loser's Shock", "id": 1928}, {"PrimaryObjective": "On-Site Refining", "SecondaryObjective": "Fossils", "Complexity": "2", "Length": "2", "CodeName": "Lucky Crypt", "id": 1929}, {"PrimaryObjective": "Elimination", "SecondaryObjective": "Boolo Caps", "MissionWarnings": ["Lithophage Outbreak"], "Complexity": "3", "Length": "3", "CodeName": "Fearful Abyss", "id": 1931}, {"PrimaryObjective": "Mining Expedition", "SecondaryObjective": "Gunk Seeds", "MissionWarnings": ["Lithophage Outbreak"], "MissionMutator": "Double XP", "Complexity": "3", "Length": "3", "CodeName": "Infested Reserve", "id": 1932}, {"PrimaryObjective": "Point Extraction", "SecondaryObjective": "Dystrum", "MissionWarnings": ["Lithophage Outbreak"], "MissionMutator": "Double XP", "Complexity": "3", "Length": "3", "CodeName": "Sharp Clearing", "id": 1933}], "Salt Pits": [{"PrimaryObjective": "Mining Expedition", "SecondaryObjective": "ApocaBlooms", "Complexity": "1", "Length": "1", "CodeName": "Rocky Prize", "id": 1927}, {"PrimaryObjective": "Egg Hunt", "SecondaryObjective": "Hollomite", "MissionWarnings": ["Mactera Plague"], "MissionMutator": "Low Gravity", "Complexity": "2", "Length": "2", "CodeName": "Bared Hook", "id": 1930}, {"PrimaryObjective": "Point Extraction", "SecondaryObjective": "Ebonuts", "MissionWarnings": ["Lithophage Outbreak"], "Complexity": "3", "Length": "2", "CodeName": "Solid Run", "id": 1934}], "Azure Weald": [{"PrimaryObjective": "Elimination", "SecondaryObjective": "Ebonuts", "Complexity": "2", "Length": "2", "CodeName": "Cruel Slope", "id": 1944}, {"PrimaryObjective": "Escort Duty", "SecondaryObjective": "Fester Fleas", "Complexity": "2", "Length": "2", "CodeName": "Weeping Thickening", "id": 1945}, {"PrimaryObjective": "On-Site Refining", "SecondaryObjective": "ApocaBlooms", "Complexity": "3", "Length": "2", "CodeName": "Dark Vault", "id": 1946}, {"PrimaryObjective": "Industrial Sabotage", "SecondaryObjective": "ApocaBlooms", "Complexity": "1", "Length": "2", "CodeName": "Fragile Force", "id": 1947}], "Radioactive Exclusion Zone": [{"PrimaryObjective": "Mining Expedition", "SecondaryObjective": "Fossils", "Complexity": "1", "Length": "2", "CodeName": "Hermit's Echo", "id": 1935}, {"PrimaryObjective": "Salvage Operation", "SecondaryObjective": "Boolo Caps", "Complexity": "2", "Length": "2", "CodeName": "Solitary Risk", "id": 1936}, {"PrimaryObjective": "Industrial Sabotage", "SecondaryObjective": "Fossils", "MissionWarnings": ["Parasites"], "MissionMutator": "Rich Atmosphere", "Complexity": "2", "Length": "2", "CodeName": "Great Bed", "id": 1937}, {"PrimaryObjective": "Elimination", "SecondaryObjective": "Boolo Caps", "MissionWarnings": ["Elite Threat"], "MissionMutator": "Golden Bugs", "Complexity": "2", "Length": "2", "CodeName": "Deadman's Gods", "id": 1938}, {"PrimaryObjective": "Egg Hunt", "SecondaryObjective": "Ebonuts", "MissionWarnings": ["Elite Threat", "Lethal Enemies"], "Complexity": "1", "Length": "1", "CodeName": "Abandoned Honor", "id": 1939}], "Hollow Bough": [{"PrimaryObjective": "Egg Hunt", "SecondaryObjective": "Boolo Caps", "Complexity": "2", "Length": "2", "CodeName": "Emerald Rock", "id": 1940}, {"PrimaryObjective": "Point Extraction", "SecondaryObjective": "Ebonuts", "Complexity": "3", "Length": "2", "CodeName": "Tainted Crib", "id": 1941}, {"PrimaryObjective": "Mining Expedition", "SecondaryObjective": "Fester Fleas", "MissionWarnings": ["Rival Presence"], "Complexity": "1", "Length": "2", "CodeName": "Gunner's Darkness", "id": 1942}, {"PrimaryObjective": "Escort Duty", "SecondaryObjective": "Fester Fleas", "MissionWarnings": ["Lethal Enemies"], "Complexity": "2", "Length": "2", "CodeName": "Jealous Grave", "id": 1943}]}, "timestamp": "2024-04-11T09:30:00Z"}, "s0": {"Biomes": {"Crystalline Caverns": [{"PrimaryObjective": "Egg Hunt", "SecondaryObjective": "ApocaBlooms", "Complexity": "1", "Length": "1", "CodeName": "Loser's Shock", "id": 1909}, {"PrimaryObjective": "On-Site Refining", "SecondaryObjective": "Fossils", "Complexity": "2", "Length": "2", "CodeName": "Lucky Crypt", "id": 1910}, {"PrimaryObjective": "Elimination", "SecondaryObjective": "Boolo Caps", "Complexity": "3", "Length": "3", "CodeName": "Fearful Abyss", "id": 1912}, {"PrimaryObjective": "Mining Expedition", "SecondaryObjective": "Gunk Seeds", "MissionMutator": "Double XP", "Complexity": "3", "Length": "3", "CodeName": "Infested Reserve", "id": 1913}], "Salt Pits": [{"PrimaryObjective": "Mining Expedition", "SecondaryObjective": "ApocaBlooms", "Complexity": "1", "Length": "1", "CodeName": "Rocky Prize", "id": 1908}, {"PrimaryObjective": "Egg Hunt", "SecondaryObjective": "Hollomite", "MissionWarnings": ["Mactera Plague"], "MissionMutator": "Low Gravity", "Complexity": "2", "Length": "2", "CodeName": "Bared Hook", "id": 1911}], "Azure Weald": [{"PrimaryObjective": "Elimination", "SecondaryObjective": "Ebonuts", "Complexity": "2", "Length": "2", "CodeName": "Cruel Slope", "id": 1923}, {"PrimaryObjective": "Escort Duty", "SecondaryObjective": "Fester Fleas", "Complexity": "2", "Length": "2", "CodeName": "Weeping Thickening", "id": 1924}, {"PrimaryObjective": "On-Site Refining", "SecondaryObjective": "ApocaBlooms", "Complexity": "3", "Length": "2", "CodeName": "Dark Vault", "id": 1925}, {"PrimaryObjective": "Industrial Sabotage", "SecondaryObjective": "ApocaBlooms", "Complexity": "1", "Length": "2", "CodeName": "Fragile Force", "id": 1926}], "Radioactive Exclusion Zone": [{"PrimaryObjective": "Mining Expedition", "SecondaryObjective": "Fossils", "Complexity": "1", "Length": "2", "CodeName": "Hermit's Echo", "id": 1914}, {"PrimaryObjective": "Salvage Operation", "SecondaryObjective": "Boolo Caps", "Complexity": "2", "Length": "2", "CodeName": "Solitary Risk", "id": 1915}, {"PrimaryObjective": "Industrial Sabotage", "SecondaryObjective": "Fossils", "MissionWarnings": ["Parasites"], "MissionMutator": "Rich Atmosphere", "Complexity": "2", "Length": "2", "CodeName": "Great Bed", "id": 1916}, {"PrimaryObjective": "Elimination", "SecondaryObjective": "Boolo Caps", "MissionWarnings": ["Elite Threat"], "MissionMutator": "Golden Bugs", "Complexity": "2", "Length": "2", "CodeName": "Deadman's Gods", "id": 1917}, {"PrimaryObjective": "Egg Hunt", "SecondaryObjective": "Ebonuts", "MissionWarnings": ["Elite Threat", "Lethal Enemies"], "Complexity": "1", "Length": "1", "CodeName": "Abandoned Honor", "id": 1918}], "Hollow Bough": [{"PrimaryObjective": "Egg Hunt", "SecondaryObjective": "Boolo Caps", "Complexity": "2", "Length": "2", "CodeName": "Emerald Rock", "id": 1919}, {"PrimaryObjective": "Point Extraction", "SecondaryObjective": "Ebonuts", "Complexity": "3", "Length": "2", "CodeName": "Tainted Crib", "id": 1920}, {"PrimaryObjective": "Mining Expedition", "SecondaryObjective": "Fester Fleas", "MissionWarnings": ["Rival Presence"], "Complexity": "1", "Length": "2", "CodeName": "Gunner's Darkness", "id": 1921}, {"PrimaryObjective": "Escort Duty", "SecondaryObjective": "Fester Fleas", "MissionWarnings": ["Lethal Enemies"], "Complexity": "2", "Length": "2", "CodeName": "Jealous Grave", "id": 1922}]}, "timestamp": "2024-04-11T09:30:00Z"}}