{"Biomes": {"Glacial Strata": [{"PrimaryObjective": "Point Extraction", "SecondaryObjective": "Dystrum", "Complexity": "3", "Length": "2", "CodeName": "Wild Gorge", "id": 8559, "season": "s0"}, {"PrimaryObjective": "Egg Hunt", "SecondaryObjective": "ApocaBlooms", "MissionWarnings": ["Lithophage Outbreak"], "Complexity": "2", "Length": "2", "CodeName": "Blunt Head", "id": 8584, "season": "s4"}], "Crystalline Caverns": [{"PrimaryObjective": "Mining Expedition", "SecondaryObjective": "Fester Fleas", "Complexity": "1", "Length": "1", "CodeName": "Barbarous Carcass", "id": 8550, "season": "s0"}, {"PrimaryObjective": "Egg Hunt", "SecondaryObjective": "Boolo Caps", "Complexity": "1", "Length": "1", "CodeName": "Naked Pocket", "id": 8551, "season": "s0"}, {"PrimaryObjective": "On-Site Refining", "SecondaryObjective": "Ebonuts", "Complexity": "2", "Length": "2", "CodeName": "Beginner's Salute", "id": 8552, "season": "s0"}, {"PrimaryObjective": "Industrial Sabotage", "SecondaryObjective": "Hollomite", "MissionWarnings": ["Parasites"], "MissionMutator": "Golden Bugs", "Complexity": "2", "Length": "2", "CodeName": "Wide Base", "id": 8553, "season": "s0"}], "Sandblasted Corridors": [{"PrimaryObjective": "Elimination", "SecondaryObjective": "Hollomite", "Complexity": "2", "Length": "2", "CodeName": "Infinity Interest", "id": 8564, "season": "s0"}, {"PrimaryObjective": "Escort Duty", "SecondaryObjective": "ApocaBlooms", "Complexity": "2", "Length": "2", "CodeName": "Distant Cellar", "id": 8565, "season": "s0"}, {"PrimaryObjective": "On-Site Refining", "SecondaryObjective": "Fossils", "Complexity": "3", "Length": "2", "CodeName": "Crying Darkness", "id": 8566, "season": "s0"}, {"PrimaryObjective": "Mining Expedition", "SecondaryObjective": "Boolo Caps", "MissionMutator": "Gold Rush", "Complexity": "1", "Length": "2", "CodeName": "Strange Tomb", "id": 8567, "season": "s0"}, {"PrimaryObjective": "Egg Hunt", "SecondaryObjective": "Hollomite", "MissionWarnings": ["Mactera Plague", "Swarmageddon"], "Complexity": "2", "Length": "2", "CodeName": "Low Skull", "id": 8568, "season": "s0"}], "Radioactive Exclusion Zone": [{"PrimaryObjective": "Mining Expedition", "SecondaryObjective": "Fester Fleas", "Complexity": "1", "Length": "2", "CodeName": "Fathomless Unfortune", "id": 8554, "season": "s0"}, {"PrimaryObjective": "Salvage Operation", "SecondaryObjective": "ApocaBlooms", "Complexity": "2", "Length": "2", "CodeName": "Feral Level", "id": 8555, "season": "s0"}, {"PrimaryObjective": "Industrial Sabotage", "SecondaryObjective": "Hollomite", "Complexity": "1", "Length": "2", "CodeName": "Unveiled Reserve", "id": 8556, "season": "s0"}, {"PrimaryObjective": "Point Extraction", "SecondaryObjective": "Fester Fleas", "MissionWarnings": ["Mactera Plague"], "MissionMutator": "Mineral Mania", "Complexity": "3", "Length": "3", "CodeName": "Driller's Earth", "id": 8557, "season": "s0"}], "Dense Biozone": [{"PrimaryObjective": "Egg Hunt", "SecondaryObjective": "Fossils", "Complexity": "2", "Length": "2", "CodeName": "Freak Armpit", "id": 8558, "season": "s0"}, {"PrimaryObjective": "Elimination", "SecondaryObjective": "Fossils", "Complexity": "3", "Length": "3", "CodeName": "Bare Foot", "id": 8563, "season": "s0"}, {"PrimaryObjective": "Elimination", "SecondaryObjective": "Fossils", "MissionWarnings": ["Lithophage Outbreak"], "Complexity": "3", "Length": "3", "CodeName": "Bare Foot", "id": 8582, "season": "s4"}, {"PrimaryObjective": "Mining Expedition", "SecondaryObjective": "Fossils", "MissionWarnings": ["Lithophage Outbreak"], "Complexity": "1", "Length": "1", "CodeName": "Solid Thunder", "id": 8583, "season": "s4"}], "Hollow Bough": [{"PrimaryObjective": "Salvage Operation", "SecondaryObjective": "ApocaBlooms", "MissionWarnings": ["Cave Leech Cluster"], "MissionMutator": "Gold Rush", "Complexity": "2", "Length": "2", "CodeName": "Awful Depths", "id": 8560, "season": "s0"}, {"PrimaryObjective": "On-Site Refining", "SecondaryObjective": "Fossils", "MissionMutator": "Volatile Guts", "Complexity": "3", "Length": "2", "CodeName": "Defect Bed", "id": 8561, "season": "s0"}, {"PrimaryObjective": "Escort Duty", "SecondaryObjective": "Gunk Seeds", "MissionWarnings": ["Mactera Plague"], "MissionMutator": "Double XP", "Complexity": "3", "Length": "3", "CodeName": "Second Gate", "id": 8562, "season": "s0"}, {"PrimaryObjective": "Elimination", "SecondaryObjective": "Gunk Seeds", "MissionWarnings": ["Lithophage Outbreak"], "Complexity": "2", "Length": "2", "CodeName": "Deep Crypt", "id": 8585, "season": "s4"}]}, "timestamp": "2024-04-14T19:30:00Z"}