{"s4": {"Biomes": {"Glacial Strata": [{"PrimaryObjective": "Egg Hunt", "SecondaryObjective": "Ebonuts", "Complexity": "2", "Length": "2", "CodeName": "Ancient Summit", "id": 5171}, {"PrimaryObjective": "Salvage Operation", "SecondaryObjective": "Gunk Seeds", "MissionWarnings": ["Lithophage Outbreak"], "Complexity": "3", "Length": "3", "CodeName": "Engineer's Salute", "id": 5175}, {"PrimaryObjective": "Elimination", "SecondaryObjective": "Fossils", "MissionWarnings": ["Lithophage Outbreak"], "Complexity": "3", "Length": "3", "CodeName": "Brisk Pocket", "id": 5180}], "Salt Pits": [{"PrimaryObjective": "Mining Expedition", "SecondaryObjective": "Hollomite", "Complexity": "1", "Length": "1", "CodeName": "Wild Fort", "id": 5163}, {"PrimaryObjective": "Egg Hunt", "SecondaryObjective": "Ebonuts", "Complexity": "1", "Length": "1", "CodeName": "Natural Hole", "id": 5164}, {"PrimaryObjective": "On-Site Refining", "SecondaryObjective": "ApocaBlooms", "Complexity": "2", "Length": "2", "CodeName": "Illuminated Lair", "id": 5165}, {"PrimaryObjective": "Industrial Sabotage", "SecondaryObjective": "Hollomite", "Complexity": "1", "Length": "2", "CodeName": "Hidden Armpit", "id": 5166}], "Magma Core": [{"PrimaryObjective": "Elimination", "SecondaryObjective": "Boolo Caps", "Complexity": "2", "Length": "2", "CodeName": "Useless Slope", "id": 5181}, {"PrimaryObjective": "Escort Duty", "SecondaryObjective": "ApocaBlooms", "Complexity": "2", "Length": "2", "CodeName": "Deep Hollow", "id": 5182}, {"PrimaryObjective": "On-Site Refining", "SecondaryObjective": "Fester Fleas", "Complexity": "3", "Length": "2", "CodeName": "Imperfect Path", "id": 5183}, {"PrimaryObjective": "Salvage Operation", "SecondaryObjective": "ApocaBlooms", "MissionWarnings": ["Lithophage Outbreak"], "Complexity": "2", "Length": "2", "CodeName": "Sunken Feast", "id": 5184}], "Radioactive Exclusion Zone": [{"PrimaryObjective": "Mining Expedition", "SecondaryObjective": "Ebonuts", "Complexity": "1", "Length": "2", "CodeName": "Weeping Overhang", "id": 5167}, {"PrimaryObjective": "Salvage Operation", "SecondaryObjective": "Gunk Seeds", "Complexity": "2", "Length": "2", "CodeName": "Dastardly End", "id": 5168}, {"PrimaryObjective": "Elimination", "SecondaryObjective": "Hollomite", "MissionWarnings": ["Cave Leech Cluster"], "Complexity": "2", "Length": "2", "CodeName": "Fractured Pursuit", "id": 5169}, {"PrimaryObjective": "Point Extraction", "SecondaryObjective": "Boolo Caps", "MissionWarnings": ["Mactera Plague"], "MissionMutator": "Rich Atmosphere", "Complexity": "3", "Length": "3", "CodeName": "Stale Depths", "id": 5170}], "Dense Biozone": [{"PrimaryObjective": "Point Extraction", "SecondaryObjective": "Gunk Seeds", "Complexity": "3", "Length": "2", "CodeName": "Cimmerian Thunder", "id": 5172}, {"PrimaryObjective": "Egg Hunt", "SecondaryObjective": "Hollomite", "MissionMutator": "Gold Rush", "Complexity": "2", "Length": "3", "CodeName": "Bleak Impact", "id": 5174}, {"PrimaryObjective": "Elimination", "SecondaryObjective": "ApocaBlooms", "MissionWarnings": ["Parasites", "Rival Presence"], "Complexity": "3", "Length": "3", "CodeName": "Colossal Jewel", "id": 5177}, {"PrimaryObjective": "Mining Expedition", "SecondaryObjective": "Ebonuts", "MissionWarnings": ["Lithophage Outbreak"], "Complexity": "2", "Length": "3", "CodeName": "Irrational Mork", "id": 5179}], "Hollow Bough": [{"PrimaryObjective": "Industrial Sabotage", "SecondaryObjective": "Hollomite", "MissionWarnings": ["Low Oxygen"], "Complexity": "2", "Length": "2", "CodeName": "Exposed Field", "id": 5173}, {"PrimaryObjective": "Salvage Operation", "SecondaryObjective": "Boolo Caps", "MissionWarnings": ["Lithophage Outbreak"], "MissionMutator": "Low Gravity", "Complexity": "2", "Length": "2", "CodeName": "Open Decay", "id": 5176}, {"PrimaryObjective": "On-Site Refining", "SecondaryObjective": "ApocaBlooms", "MissionWarnings": ["Lithophage Outbreak"], "MissionMutator": "Low Gravity", "Complexity": "2", "Length": "2", "CodeName": "Awful Senit", "id": 5178}]}, "timestamp": "2024-04-13T01:30:00Z"}, "s0": {"Biomes": {"Glacial Strata": [{"PrimaryObjective": "Egg Hunt", "SecondaryObjective": "Ebonuts", "Complexity": "2", "Length": "2", "CodeName": "Ancient Summit", "id": 5152}, {"PrimaryObjective": "Salvage Operation", "SecondaryObjective": "Gunk Seeds", "Complexity": "3", "Length": "3", "CodeName": "Engineer's Salute", "id": 5156}], "Salt Pits": [{"PrimaryObjective": "Mining Expedition", "SecondaryObjective": "Hollomite", "Complexity": "1", "Length": "1", "CodeName": "Wild Fort", "id": 5144}, {"PrimaryObjective": "Egg Hunt", "SecondaryObjective": "Ebonuts", "Complexity": "1", "Length": "1", "CodeName": "Natural Hole", "id": 5145}, {"PrimaryObjective": "On-Site Refining", "SecondaryObjective": "ApocaBlooms", "Complexity": "2", "Length": "2", "CodeName": "Illuminated Lair", "id": 5146}, {"PrimaryObjective": "Industrial Sabotage", "SecondaryObjective": "Hollomite", "Complexity": "1", "Length": "2", "CodeName": "Hidden Armpit", "id": 5147}], "Magma Core": [{"PrimaryObjective": "Elimination", "SecondaryObjective": "Boolo Caps", "Complexity": "2", "Length": "2", "CodeName": "Useless Slope", "id": 5159}, {"PrimaryObjective": "Escort Duty", "SecondaryObjective": "ApocaBlooms", "Complexity": "2", "Length": "2", "CodeName": "Deep Hollow", "id": 5160}, {"PrimaryObjective": "On-Site Refining", "SecondaryObjective": "Fester Fleas", "Complexity": "3", "Length": "2", "CodeName": "Imperfect Path", "id": 5161}, {"PrimaryObjective": "Salvage Operation", "SecondaryObjective": "ApocaBlooms", "MissionWarnings": ["Lithophage Outbreak"], "Complexity": "2", "Length": "2", "CodeName": "Sunken Feast", "id": 5162}], "Radioactive Exclusion Zone": [{"PrimaryObjective": "Mining Expedition", "SecondaryObjective": "Ebonuts", "Complexity": "1", "Length": "2", "CodeName": "Weeping Overhang", "id": 5148}, {"PrimaryObjective": "Salvage Operation", "SecondaryObjective": "Gunk Seeds", "Complexity": "2", "Length": "2", "CodeName": "Dastardly End", "id": 5149}, {"PrimaryObjective": "Elimination", "SecondaryObjective": "Hollomite", "MissionWarnings": ["Cave Leech Cluster"], "Complexity": "2", "Length": "2", "CodeName": "Fractured Pursuit", "id": 5150}, {"PrimaryObjective": "Point Extraction", "SecondaryObjective": "Boolo Caps", "MissionWarnings": ["Mactera Plague"], "MissionMutator": "Rich Atmosphere", "Complexity": "3", "Length": "3", "CodeName": "Stale Depths", "id": 5151}], "Dense Biozone": [{"PrimaryObjective": "Point Extraction", "SecondaryObjective": "Gunk Seeds", "Complexity": "3", "Length": "2", "CodeName": "Cimmerian Thunder", "id": 5153}, {"PrimaryObjective": "Egg Hunt", "SecondaryObjective": "Hollomite", "MissionMutator": "Gold Rush", "Complexity": "2", "Length": "3", "CodeName": "Bleak Impact", "id": 5155}, {"PrimaryObjective": "Elimination", "SecondaryObjective": "ApocaBlooms", "MissionWarnings": ["Parasites", "Rival Presence"], "Complexity": "3", "Length": "3", "CodeName": "Colossal Jewel", "id": 5158}], "Hollow Bough": [{"PrimaryObjective": "Industrial Sabotage", "SecondaryObjective": "Hollomite", "MissionWarnings": ["Low Oxygen"], "Complexity": "2", "Length": "2", "CodeName": "Exposed Field", "id": 5154}, {"PrimaryObjective": "Salvage Operation", "SecondaryObjective": "Boolo Caps", "MissionMutator": "Low Gravity", "Complexity": "2", "Length": "2", "CodeName": "Open Decay", "id": 5157}]}, "timestamp": "2024-04-13T01:30:00Z"}}