{"Biomes": {"Crystalline Caverns": [{"PrimaryObjective": "Mining Expedition", "SecondaryObjective": "Fester Fleas", "Complexity": "1", "Length": "1", "CodeName": "Bleak Downfall", "id": 11340, "season": "s0"}, {"PrimaryObjective": "Egg Hunt", "SecondaryObjective": "Boolo Caps", "Complexity": "1", "Length": "1", "CodeName": "Hideous Clearing", "id": 11341, "season": "s0"}, {"PrimaryObjective": "On-Site Refining", "SecondaryObjective": "ApocaBlooms", "Complexity": "2", "Length": "2", "CodeName": "Driller's Gap", "id": 11342, "season": "s0"}, {"PrimaryObjective": "Industrial Sabotage", "SecondaryObjective": "Boolo Caps", "Complexity": "1", "Length": "2", "CodeName": "Scarred Claw", "id": 11343, "season": "s0"}], "Magma Core": [{"PrimaryObjective": "Elimination", "SecondaryObjective": "Fester Fleas", "Complexity": "2", "Length": "2", "CodeName": "Sunken Border", "id": 11352, "season": "s0"}, {"PrimaryObjective": "Escort Duty", "SecondaryObjective": "Gunk Seeds", "MissionMutator": "Low Gravity", "Complexity": "2", "Length": "2", "CodeName": "Dark Foot", "id": 11357, "season": "s0"}, {"PrimaryObjective": "Mining Expedition", "SecondaryObjective": "ApocaBlooms", "MissionWarnings": ["Lithophage Outbreak"], "Complexity": "2", "Length": "3", "CodeName": "Sharp Force", "id": 11379, "season": "s4"}], "Azure Weald": [{"PrimaryObjective": "On-Site Refining", "SecondaryObjective": "ApocaBlooms", "Complexity": "3", "Length": "2", "CodeName": "Mythic Outback", "id": 11354, "season": "s0"}, {"PrimaryObjective": "Industrial Sabotage", "SecondaryObjective": "Fossils", "Complexity": "2", "Length": "2", "CodeName": "Second Interest", "id": 11355, "season": "s0"}, {"PrimaryObjective": "Egg Hunt", "SecondaryObjective": "Fester Fleas", "Complexity": "2", "Length": "3", "CodeName": "Low Expanse", "id": 11356, "season": "s0"}, {"PrimaryObjective": "Industrial Sabotage", "SecondaryObjective": "Fossils", "MissionWarnings": ["Lithophage Outbreak"], "Complexity": "2", "Length": "2", "CodeName": "Second Interest", "id": 11374, "season": "s4"}, {"PrimaryObjective": "Egg Hunt", "SecondaryObjective": "Fester Fleas", "MissionWarnings": ["Lithophage Outbreak"], "Complexity": "2", "Length": "3", "CodeName": "Low Expanse", "id": 11375, "season": "s4"}, {"PrimaryObjective": "Mining Expedition", "SecondaryObjective": "Ebonuts", "MissionWarnings": ["Lithophage Outbreak"], "Complexity": "1", "Length": "1", "CodeName": "Everlasting Jewel", "id": 11378, "season": "s4"}], "Sandblasted Corridors": [{"PrimaryObjective": "Escort Duty", "SecondaryObjective": "Fester Fleas", "Complexity": "2", "Length": "2", "CodeName": "Fearful Delight", "id": 11353, "season": "s0"}, {"PrimaryObjective": "Egg Hunt", "SecondaryObjective": "Ebonuts", "MissionWarnings": ["Cave Leech Cluster", "Haunted Cave"], "Complexity": "1", "Length": "1", "CodeName": "Natural Reserve", "id": 11358, "season": "s0"}, {"PrimaryObjective": "Egg Hunt", "SecondaryObjective": "Fossils", "MissionWarnings": ["Lithophage Outbreak"], "Complexity": "2", "Length": "3", "CodeName": "Furious Thickening", "id": 11380, "season": "s4"}], "Radioactive Exclusion Zone": [{"PrimaryObjective": "Mining Expedition", "SecondaryObjective": "Hollomite", "Complexity": "1", "Length": "2", "CodeName": "Unveiled Pass", "id": 11344, "season": "s0"}, {"PrimaryObjective": "Salvage Operation", "SecondaryObjective": "ApocaBlooms", "Complexity": "2", "Length": "2", "CodeName": "Naked Nest", "id": 11345, "season": "s0"}, {"PrimaryObjective": "Egg Hunt", "SecondaryObjective": "Boolo Caps", "MissionWarnings": ["Rival Presence"], "MissionMutator": "Rich Atmosphere", "Complexity": "2", "Length": "2", "CodeName": "Gunner's Ledge", "id": 11346, "season": "s0"}, {"PrimaryObjective": "On-Site Refining", "SecondaryObjective": "Fester Fleas", "MissionMutator": "Volatile Guts", "Complexity": "3", "Length": "2", "CodeName": "Mammoth Sadness", "id": 11347, "season": "s0"}], "Hollow Bough": [{"PrimaryObjective": "Egg Hunt", "SecondaryObjective": "Ebonuts", "Complexity": "2", "Length": "2", "CodeName": "Covered Guts", "id": 11348, "season": "s0"}, {"PrimaryObjective": "Point Extraction", "SecondaryObjective": "Ebonuts", "Complexity": "3", "Length": "2", "CodeName": "Creeping Vault", "id": 11349, "season": "s0"}, {"PrimaryObjective": "Escort Duty", "SecondaryObjective": "Fester Fleas", "MissionMutator": "Critical Weakness", "Complexity": "2", "Length": "3", "CodeName": "Warrior's Bottom", "id": 11350, "season": "s0"}, {"PrimaryObjective": "Elimination", "SecondaryObjective": "Fester Fleas", "MissionWarnings": ["Haunted Cave"], "MissionMutator": "Gold Rush", "Complexity": "2", "Length": "2", "CodeName": "Shattered Shelf", "id": 11351, "season": "s0"}]}, "timestamp": "2024-04-16T06:00:00Z"}