{"Biomes": {"Salt Pits": [{"PrimaryObjective": "Mining Expedition", "SecondaryObjective": "ApocaBlooms", "Complexity": "1", "Length": "1", "CodeName": "Strange Rock", "id": 11542, "season": "s0"}, {"PrimaryObjective": "Egg Hunt", "SecondaryObjective": "Fester Fleas", "Complexity": "1", "Length": "1", "CodeName": "Dastardly Ideal", "id": 11543, "season": "s0"}, {"PrimaryObjective": "On-Site Refining", "SecondaryObjective": "Fossils", "Complexity": "2", "Length": "2", "CodeName": "Stony Armpit", "id": 11544, "season": "s0"}, {"PrimaryObjective": "Point Extraction", "SecondaryObjective": "ApocaBlooms", "MissionWarnings": ["Lethal Enemies"], "Complexity": "3", "Length": "2", "CodeName": "Shattered Earth", "id": 11545, "season": "s0"}], "Azure Weald": [{"PrimaryObjective": "Elimination", "SecondaryObjective": "ApocaBlooms", "Complexity": "2", "Length": "2", "CodeName": "Jagged Run", "id": 11556, "season": "s0"}, {"PrimaryObjective": "Escort Duty", "SecondaryObjective": "ApocaBlooms", "Complexity": "2", "Length": "2", "CodeName": "Infernal Palace", "id": 11557, "season": "s0"}, {"PrimaryObjective": "On-Site Refining", "SecondaryObjective": "Fossils", "Complexity": "3", "Length": "2", "CodeName": "Engineer's Drift", "id": 11558, "season": "s0"}, {"PrimaryObjective": "Industrial Sabotage", "SecondaryObjective": "Fossils", "MissionWarnings": ["Exploder Infestation"], "Complexity": "2", "Length": "2", "CodeName": "Divine Face", "id": 11559, "season": "s0"}, {"PrimaryObjective": "Mining Expedition", "SecondaryObjective": "ApocaBlooms", "MissionWarnings": ["Low Oxygen", "Swarmageddon"], "Complexity": "1", "Length": "1", "CodeName": "Titanic Fury", "id": 11560, "season": "s0"}], "Fungus Bogs": [{"PrimaryObjective": "Mining Expedition", "SecondaryObjective": "Hollomite", "Complexity": "1", "Length": "2", "CodeName": "Bad Carcass", "id": 11546, "season": "s0"}, {"PrimaryObjective": "Industrial Sabotage", "SecondaryObjective": "Fossils", "Complexity": "1", "Length": "2", "CodeName": "Defect Trick", "id": 11548, "season": "s0"}, {"PrimaryObjective": "Salvage Operation", "SecondaryObjective": "ApocaBlooms", "Complexity": "3", "Length": "3", "CodeName": "Unrobed Passage", "id": 11551, "season": "s0"}, {"PrimaryObjective": "Salvage Operation", "SecondaryObjective": "ApocaBlooms", "MissionWarnings": ["Lithophage Outbreak"], "Complexity": "3", "Length": "3", "CodeName": "Unrobed Passage", "id": 11570, "season": "s4"}, {"PrimaryObjective": "Point Extraction", "SecondaryObjective": "Hollomite", "MissionWarnings": ["Lithophage Outbreak"], "Complexity": "3", "Length": "2", "CodeName": "Illuminated Bones", "id": 11571, "season": "s4"}], "Radioactive Exclusion Zone": [{"PrimaryObjective": "Salvage Operation", "SecondaryObjective": "Fossils", "Complexity": "2", "Length": "2", "CodeName": "Crying Heart", "id": 11547, "season": "s0"}, {"PrimaryObjective": "Egg Hunt", "SecondaryObjective": "Boolo Caps", "Complexity": "2", "Length": "3", "CodeName": "Useless Fear", "id": 11549, "season": "s0"}, {"PrimaryObjective": "Escort Duty", "SecondaryObjective": "ApocaBlooms", "MissionWarnings": ["Low Oxygen"], "Complexity": "3", "Length": "3", "CodeName": "Full Level", "id": 11550, "season": "s0"}, {"PrimaryObjective": "Egg Hunt", "SecondaryObjective": "Boolo Caps", "MissionWarnings": ["Lithophage Outbreak"], "Complexity": "2", "Length": "3", "CodeName": "Useless Fear", "id": 11568, "season": "s4"}, {"PrimaryObjective": "Mining Expedition", "SecondaryObjective": "Boolo Caps", "MissionWarnings": ["Lithophage Outbreak"], "Complexity": "1", "Length": "2", "CodeName": "Rough Crypt", "id": 11572, "season": "s4"}], "Dense Biozone": [{"PrimaryObjective": "Egg Hunt", "SecondaryObjective": "Hollomite", "Complexity": "2", "Length": "2", "CodeName": "Peeled Abyss", "id": 11552, "season": "s0"}, {"PrimaryObjective": "Point Extraction", "SecondaryObjective": "Hollomite", "Complexity": "3", "Length": "2", "CodeName": "Rippled Chamber", "id": 11553, "season": "s0"}, {"PrimaryObjective": "Elimination", "SecondaryObjective": "Ebonuts", "MissionWarnings": ["Exploder Infestation"], "Complexity": "3", "Length": "3", "CodeName": "Xehn's Hulrum", "id": 11554, "season": "s0"}, {"PrimaryObjective": "Mining Expedition", "SecondaryObjective": "Fossils", "MissionMutator": "Critical Weakness", "Complexity": "1", "Length": "1", "CodeName": "Petrified Base", "id": 11555, "season": "s0"}]}, "timestamp": "2024-04-16T08:30:00Z"}